dalabase/__init__.py
dalabase/core.py
dalabase-0.0.1.dist-info/LICENSE
dalabase-0.0.1.dist-info/METADATA
dalabase-0.0.1.dist-info/WHEEL
dalabase-0.0.1.dist-info/RECORD
